bowline/__init__.py
bowline/models/__init__.py
bowline/models/chain.py
bowline/models/graph.py
bowline/models/processor.py
bowline/models/result.py
bowline/utils/__init__.py
bowline/utils/config.py
bowline/utils/logger.py
bowline_streaming-0.5.0.dist-info/LICENSE
bowline_streaming-0.5.0.dist-info/METADATA
bowline_streaming-0.5.0.dist-info/WHEEL
bowline_streaming-0.5.0.dist-info/top_level.txt
bowline_streaming-0.5.0.dist-info/RECORD
