Metadata-Version: 2.1
Name: bowline-streaming
Version: 0.5.0
Summary: Bowline: Easily build performant data stream processing pipelines in Python.
Author-email: Scott Barnes <sgbarnes@protonmail.com>
Project-URL: Homepage, https://github.com/scottbarnesg/bowline
Project-URL: Bug Tracker, https://github.com/scottbarnesg/bowline/issues
Classifier: Programming Language :: Python :: 3
Classifier: License :: OSI Approved :: MIT License
Classifier: Operating System :: OS Independent
Requires-Python: >=3
License-File: LICENSE
Requires-Dist: pydantic
Requires-Dist: pyyaml >=6.0.1
Provides-Extra: dev
Requires-Dist: pytest ; extra == 'dev'
